constituent_treelib/__init__.py
constituent_treelib/core.py
constituent_treelib/errors.py
constituent_treelib/export.py
constituent_treelib-0.0.8.dist-info/METADATA
constituent_treelib-0.0.8.dist-info/WHEEL
constituent_treelib-0.0.8.dist-info/licenses/LICENSE
constituent_treelib-0.0.8.dist-info/RECORD
