Metadata-Version: 2.3
Name: constituent_treelib
Version: 0.0.8
Summary: A lightweight Python library for constructing, processing, and visualizing constituent trees.
Project-URL: Homepage, https://github.com/Halvani/constituent-treelib
Project-URL: Bug Tracker, https://github.com/Halvani/constituent-treelib/issues
Author: Oren Halvani
Keywords: constituency-parser,constituency-tree,export-to-pdf,export-to-png,export-to-svg,phrase-extraction,visualization
Classifier: Development Status :: 5 - Production/Stable
Classifier: Intended Audience :: Developers
Classifier: License :: OSI Approved :: MIT License
Classifier: Operating System :: OS Independent
Classifier: Programming Language :: Python :: 3.9
Classifier: Programming Language :: Python :: 3.10
Classifier: Programming Language :: Python :: 3.11
Classifier: Programming Language :: Python :: 3.12
Requires-Python: >=3.9
Requires-Dist: benepar
Requires-Dist: contractions
Requires-Dist: huspacy
Requires-Dist: ipython
Requires-Dist: langid
Requires-Dist: nltk
Requires-Dist: pdfkit
Requires-Dist: protobuf==3.20.3
Requires-Dist: pytest
Requires-Dist: spacy
Requires-Dist: streamlit
Requires-Dist: svgling
Requires-Dist: tokenizers
Requires-Dist: torch
Requires-Dist: transformers[torch]
Requires-Dist: wand
